plot_likert/__init__.py
plot_likert/colors.py
plot_likert/interval.py
plot_likert/plot_likert.py
plot_likert/scales.py
tests/__init__.py
tests/test_interval.py
plot_likert-0.5.0.dist-info/LICENSE
plot_likert-0.5.0.dist-info/METADATA
plot_likert-0.5.0.dist-info/WHEEL
plot_likert-0.5.0.dist-info/top_level.txt
plot_likert-0.5.0.dist-info/RECORD
