Metadata-Version: 2.1
Name: plot-likert
Version: 0.5.0
Summary: Library to visualize results from Likert-style survey questions
Home-page: https://github.com/nmalkin/plot-likert
Author: nmalkin
Keywords: plot graph visualize likert survey matplotlib
Classifier: Programming Language :: Python :: 3
Classifier: License :: OSI Approved :: BSD License
Classifier: Operating System :: OS Independent
Classifier: Development Status :: 3 - Alpha
Classifier: Topic :: Scientific/Engineering :: Visualization
Requires-Python: >=3.6
License-File: LICENSE
Requires-Dist: matplotlib >=3.4.0
Requires-Dist: numpy
Requires-Dist: pandas
